karrio/mappers/colissimo/__init__.py
karrio/mappers/colissimo/mapper.py
karrio/mappers/colissimo/proxy.py
karrio/mappers/colissimo/settings.py
karrio/plugins/colissimo/__init__.py
karrio/providers/colissimo/__init__.py
karrio/providers/colissimo/error.py
karrio/providers/colissimo/tracking.py
karrio/providers/colissimo/units.py
karrio/providers/colissimo/utils.py
karrio/providers/colissimo/shipment/__init__.py
karrio/providers/colissimo/shipment/create.py
karrio/schemas/colissimo/__init__.py
karrio/schemas/colissimo/error_response.py
karrio/schemas/colissimo/label_request.py
karrio/schemas/colissimo/label_response.py
karrio/schemas/colissimo/tracking_request.py
karrio/schemas/colissimo/tracking_response.py
karrio_colissimo-2026.1.4.dist-info/METADATA
karrio_colissimo-2026.1.4.dist-info/WHEEL
karrio_colissimo-2026.1.4.dist-info/entry_points.txt
karrio_colissimo-2026.1.4.dist-info/top_level.txt
karrio_colissimo-2026.1.4.dist-info/RECORD
