Metadata-Version: 2.4
Name: karrio_colissimo
Version: 2026.1.4
Summary: Karrio - Colissimo Shipping Extension
Author-email: karrio <hello@karrio.io>
License-Expression: LGPL-3.0
Project-URL: Homepage, https://github.com/karrioapi/karrio
Classifier: Intended Audience :: Developers
Classifier: Operating System :: OS Independent
Classifier: Programming Language :: Python :: 3
Requires-Python: >=3.7
Requires-Dist: karrio
